pelican/plugins/search/__init__.py
pelican/plugins/search/search.py
pelican_search-1.0.2.dist-info/METADATA
pelican_search-1.0.2.dist-info/WHEEL
pelican_search-1.0.2.dist-info/RECORD
